element_deeplabcut/__init__.py
element_deeplabcut/model.py
element_deeplabcut/train.py
element_deeplabcut/version.py
element_deeplabcut/export/__init__.py
element_deeplabcut/export/nwb.py
element_deeplabcut/readers/__init__.py
element_deeplabcut/readers/dlc_reader.py
element_deeplabcut-0.2.8.dist-info/LICENSE
element_deeplabcut-0.2.8.dist-info/METADATA
element_deeplabcut-0.2.8.dist-info/WHEEL
element_deeplabcut-0.2.8.dist-info/top_level.txt
element_deeplabcut-0.2.8.dist-info/RECORD
