Metadata-Version: 2.1
Name: element-deeplabcut
Version: 0.2.8
Summary: DataJoint Element for Continuous Behavior Tracking via DeepLabCut
Home-page: https://github.com/datajoint/element-deeplabcut
Author: DataJoint
Author-email: info@vathes.com
License: MIT
Keywords: neuroscience behavior deeplabcut datajoint
Platform: UNKNOWN
License-File: LICENSE
Requires-Dist: datajoint >=0.13
Requires-Dist: deeplabcut[tf] >=2.2.1.1
Requires-Dist: element-interface >=0.3.0
Requires-Dist: opencv-python-headless
